bci_essentials/__init__.py
bci_essentials/bci_controller.py
bci_essentials/channel_selection.py
bci_essentials/resting_state.py
bci_essentials/session_saving.py
bci_essentials/signal_processing.py
bci_essentials/classification/erp_rg_classifier.py
bci_essentials/classification/erp_single_channel_classifier.py
bci_essentials/classification/generic_classifier.py
bci_essentials/classification/mi_classifier.py
bci_essentials/classification/null_classifier.py
bci_essentials/classification/ssvep_basic_tf_classifier.py
bci_essentials/classification/ssvep_riemannian_mdm_classifier.py
bci_essentials/classification/switch_mdm_classifier.py
bci_essentials/data_tank/data_tank.py
bci_essentials/io/lsl_messenger.py
bci_essentials/io/lsl_sources.py
bci_essentials/io/messenger.py
bci_essentials/io/sources.py
bci_essentials/io/xdf_sources.py
bci_essentials/paradigm/mi_paradigm.py
bci_essentials/paradigm/p300_paradigm.py
bci_essentials/paradigm/paradigm.py
bci_essentials/paradigm/ssvep_paradigm.py
bci_essentials/utils/logger.py
bci_essentials/utils/reduce_to_single_channel.py
tests/__init__.py
tests/test_classifier_save.py
tests/test_eeg_data.py
tests/test_lsl_sources.py
tests/test_signal_processing.py
tests/test_smoke.py
tests/test_trial_saving.py
tests/test_xdf_sources.py
bci_essentials-0.2.2.dist-info/LICENSE
bci_essentials-0.2.2.dist-info/METADATA
bci_essentials-0.2.2.dist-info/WHEEL
bci_essentials-0.2.2.dist-info/top_level.txt
bci_essentials-0.2.2.dist-info/RECORD
