Metadata-Version: 2.1
Name: bci-essentials
Version: 0.2.2
Summary: Python backend for bci-essentials
Requires-Python: >=3.10
License-File: LICENSE
Requires-Dist: numpy
Requires-Dist: scipy
Requires-Dist: scikit-learn
Requires-Dist: joblib
Requires-Dist: pandas
Requires-Dist: pylsl
Requires-Dist: pyxdf
Requires-Dist: matplotlib
Requires-Dist: seaborn
Requires-Dist: wheel
Requires-Dist: pyriemann
